rtscli.py
rtscli-0.4.2.dist-info/METADATA
rtscli-0.4.2.dist-info/WHEEL
rtscli-0.4.2.dist-info/entry_points.txt
rtscli-0.4.2.dist-info/top_level.txt
rtscli-0.4.2.dist-info/RECORD
